selenol_python/__init__.py
selenol_python/connections.py
selenol_python/data_structures.py
selenol_python/exceptions.py
selenol_python/params.py
selenol_python/persistences.py
selenol_python/services.py
selenol_python-0.1.dist-info/DESCRIPTION.rst
selenol_python-0.1.dist-info/METADATA
selenol_python-0.1.dist-info/RECORD
selenol_python-0.1.dist-info/WHEEL
selenol_python-0.1.dist-info/metadata.json
selenol_python-0.1.dist-info/top_level.txt
